odoo/addons/account_move_tag/README.rst
odoo/addons/account_move_tag/__init__.py
odoo/addons/account_move_tag/__manifest__.py
odoo/addons/account_move_tag/i18n/account_move_tag.pot
odoo/addons/account_move_tag/i18n/it.po
odoo/addons/account_move_tag/i18n/nl.po
odoo/addons/account_move_tag/models/__init__.py
odoo/addons/account_move_tag/models/account_move.py
odoo/addons/account_move_tag/models/account_move_line.py
odoo/addons/account_move_tag/models/account_move_tag.py
odoo/addons/account_move_tag/readme/CONTRIBUTORS.md
odoo/addons/account_move_tag/readme/DESCRIPTION.md
odoo/addons/account_move_tag/security/ir.model.access.csv
odoo/addons/account_move_tag/static/description/icon.png
odoo/addons/account_move_tag/static/description/index.html
odoo/addons/account_move_tag/views/account_move_line_views.xml
odoo/addons/account_move_tag/views/account_move_tag_menu_views.xml
odoo/addons/account_move_tag/views/account_move_tag_views.xml
odoo/addons/account_move_tag/views/account_move_views.xml
odoo_addon_account_move_tag-17.0.1.0.0.6.dist-info/METADATA
odoo_addon_account_move_tag-17.0.1.0.0.6.dist-info/WHEEL
odoo_addon_account_move_tag-17.0.1.0.0.6.dist-info/top_level.txt
odoo_addon_account_move_tag-17.0.1.0.0.6.dist-info/RECORD
