Metadata-Version: 2.1
Name: odoo-addon-account_move_tag
Version: 17.0.1.0.0.6
Requires-Python: >=3.10
Requires-Dist: odoo>=17.0a,<17.1dev
Summary: Adds tags to the account move so vendor bills and customer invoices can be easily distinguished in the accounting journal.
Home-page: https://github.com/OCA/account-invoicing
License: AGPL-3
Author: Codeforward B.V., Odoo Community Association (OCA)
Author-email: support@odoo-community.org
Classifier: Programming Language :: Python
Classifier: Framework :: Odoo
Classifier: Framework :: Odoo :: 17.0
Classifier: License :: OSI Approved :: GNU Affero General Public License v3
